lab-02/nandgate/nandgate.v
module nandgate(a,b,y);
input a,b;
output y;

nand(y,a,b);

endmodule

lab-02/nandgate/nandgate_tb.v
module nandgate_tb;
reg a,b;
wire y;

nandgate uut(a,b,y);
initial begin

$dumpfile("test_nand.vcd");
$dumpvars(0,nandgate_tb);
a = 0;
b = 0;
#5
a = 0;
b = 1;
#5
a = 1;
b = 0;
#5
a = 1;
b = 1;
#5
a = 0;
b = 0;
#5
a = 0;
b = 1;
#5
a = 1;
b = 0;
#5
a = 1;
b = 1;
#5
a = 0;
b = 0;
$finish();
end 
endmodule

lab-02/nandgate/test_nand.vcd
$date
	Sun Nov 12 12:57:12 2023
$end
$version
	Icarus Verilog
$end
$timescale
	1s
$end
$scope module nandgate_tb $end
$var wire 1 ! y $end
$var reg 1 " a $end
$var reg 1 # b $end
$scope module uut $end
$var wire 1 " a $end
$var wire 1 # b $end
$var wire 1 ! y $end
$upscope $end
$upscope $end
$enddefinitions $end
#0
$dumpvars
0#
0"
1!
$end
#5
1#
#10
0#
1"
#15
0!
1#
#20
1!
0#
0"
#25
1#
#30
0#
1"
#35
0!
1#
#40
1!
0#
0"
