lab-02/x-or/xorgate.v
module xorgate(a,b,y);
input a,b;
output y;
xor(y,a,b);
endmodule

lab-02/x-or/xorgate_tb.v
module xorgate_tb;
reg a,b;
wire y;
xorgate uut(a,b,y);
initial begin
$dumpfile("test_xor.vcd");
$dumpvars(0,xorgate_tb);
a = 0;
b = 0;
#5
a = 0;
b = 1;
#5
a = 1;
b = 0;
#5
a = 1;
b = 1;
#5
a = 0;
b = 0;
#5
a = 0;
b = 1;
#5
a = 1;
b = 0;
#5
a = 1;
b = 1;
#5
a = 0;
b = 0;
$finish();
end 
endmodule

lab-02/x-or/test_xor.vcd
$date
	Sun Nov 12 12:58:40 2023
$end
$version
	Icarus Verilog
$end
$timescale
	1s
$end
$scope module xorgate_tb $end
$var wire 1 ! y $end
$var reg 1 " a $end
$var reg 1 # b $end
$scope module uut $end
$var wire 1 " a $end
$var wire 1 # b $end
$var wire 1 ! y $end
$upscope $end
$upscope $end
$enddefinitions $end
#0
$dumpvars
0#
0"
0!
$end
#5
1!
1#
#10
0#
1"
#15
0!
1#
#20
0#
0"
#25
1!
1#
#30
0#
1"
#35
0!
1#
#40
0#
0"
