lab-02/andgate/andgate.v
module and_gate(y,a,b);
input a,b;
output y;
and(y,a,b);
endmodule

lab-02/andgate/andgate_tb.v
module and_gate_tb;
reg a,b;
wire y;
and_gate uut(y,a,b);
initial begin
$dumpfile("test_and.vcd");
$dumpvars(0,and_gate_tb);
a = 0;
b = 0;
#5
a = 0;
b = 1;
#5
a = 1;
b = 0;
#5
a = 1;
b = 1;
#5
a = 0;
b = 0;
#5
a = 0;
b = 1;
#5
a = 1;
b = 0;
#5
a = 1;
b = 1;
#5
a = 0;
b = 0;
$finish();
end 
endmodule

lab-02/andgate/test_and.vcd
$date
	Sun Nov 12 12:55:24 2023
$end
$version
	Icarus Verilog
$end
$timescale
	1s
$end
$scope module and_gate_tb $end
$var wire 1 ! y $end
$var reg 1 " a $end
$var reg 1 # b $end
$scope module uut $end
$var wire 1 " a $end
$var wire 1 # b $end
$var wire 1 ! y $end
$upscope $end
$upscope $end
$enddefinitions $end
#0
$dumpvars
0#
0"
0!
$end
#5
1#
#10
0#
1"
#15
1!
1#
#20
0!
0#
0"
#25
1#
#30
0#
1"
#35
1!
1#
#40
0!
0#
0"
