lab-05/mux.v
module mux(i0,i1,i2,i3,i4,i5,i6,i7,s0,s1,s2,y);
  input i0, i1, i2, i3, i4, i5, i6, i7, s0, s1, s2;
  output y;

  assign y = (i0 & ~s0 & ~s1 & ~s2) | (i1 & ~s0 & ~s1 & s2) | (i2 & ~s0 & s1 & ~s2) | (i3 & ~s0 & s1 & s2) | 
    (i4 & s0 & ~s1 & ~s2) | (i5 & s0 & ~s1 & s2) | (i6 & s0 & s1 & ~s2) | (i7 & s0 & s1 & s2);

endmodule

lab-05/mux_tb.v
module mux_tb;
reg i0,i1,i2,i3,i4,i5,i6,i7,s0,s1,s2;
wire y;

mux uut(i0,i1,i2,i3,i4,i5,i6,i7,s0,s1,s2,y);

initial begin
$dumpfile("test.vcd");
$dumpvars(0, mux_tb);
s0 = 0; s1 = 0; s2 = 0; i0 = 1; i1 = 0; i2 = 0; i3 = 0; i4 = 0; i5 = 0; i6 = 0; i7 = 0;
#2.5;
s0 = 0; s1 = 0; s2 = 0; i0 = 0; i1 = 0; i2 = 0; i3 = 0; i4 = 0; i5 = 0; i6 = 0; i7 = 0;
#2.5;
s0 = 0; s1 = 0; s2 = 1; i0 = 0; i1 = 1; i2 = 0; i3 = 0; i4 = 0; i5 = 0; i6 = 0; i7 = 0;
#2.5;
s0 = 0; s1 = 0; s2 = 1; i0 = 0; i1 = 0; i2 = 0; i3 = 0; i4 = 0; i5 = 0; i6 = 0; i7 = 0;
#2.5;
s0 = 0; s1 = 1; s2 = 0; i0 = 0; i1 = 0; i2 = 1; i3 = 0; i4 = 0; i5 = 0; i6 = 0; i7 = 0;
#2.5;
s0 = 0; s1 = 1; s2 = 0; i0 = 0; i1 = 0; i2 = 0; i3 = 0; i4 = 0; i5 = 0; i6 = 0; i7 = 0;
#2.5;
s0 = 0; s1 = 1; s2 = 1; i0 = 0; i1 = 0; i2 = 0; i3 = 1; i4 = 0; i5 = 0; i6 = 0; i7 = 0;
#2.5;
s0 = 0; s1 = 1; s2 = 1; i0 = 0; i1 = 0; i2 = 0; i3 = 0; i4 = 0; i5 = 0; i6 = 0; i7 = 0;
#2.5;
s0 = 1; s1 = 0; s2 = 0; i0 = 0; i1 = 0; i2 = 0; i3 = 0; i4 = 1; i5 = 0; i6 = 0; i7 = 0;
#2.5;
s0 = 1; s1 = 0; s2 = 0; i0 = 0; i1 = 0; i2 = 0; i3 = 0; i4 = 0; i5 = 0; i6 = 0; i7 = 0;
#2.5;
s0 = 1; s1 = 0; s2 = 1; i0 = 0; i1 = 0; i2 = 0; i3 = 0; i4 = 0; i5 = 1; i6 = 0; i7 = 0;
#2.5;
s0 = 1; s1 = 0; s2 = 1; i0 = 0; i1 = 0; i2 = 0; i3 = 0; i4 = 0; i5 = 0; i6 = 0; i7 = 0;
#2.5;
s0 = 1; s1 = 1; s2 = 0; i0 = 0; i1 = 0; i2 = 0; i3 = 0; i4 = 0; i5 = 0; i6 = 1; i7 = 0;
#2.5;
s0 = 1; s1 = 1; s2 = 0; i0 = 0; i1 = 0; i2 = 0; i3 = 0; i4 = 0; i5 = 0; i6 = 0; i7 = 0;
#2.5;
s0 = 1; s1 = 1; s2 = 1; i0 = 0; i1 = 0; i2 = 0; i3 = 0; i4 = 0; i5 = 0; i6 = 0; i7 = 1;
#2.5;
s0 = 1; s1 = 1; s2 = 1; i0 = 0; i1 = 0; i2 = 0; i3 = 0; i4 = 0; i5 = 0; i6 = 0; i7 = 0;
#2.5;

$finish();
end
endmodule

lab-05/test.vcd
$date
	Sun Nov 12 22:48:42 2023
$end
$version
	Icarus Verilog
$end
$timescale
	1s
$end
$scope module mux_tb $end
$var wire 1 ! y $end
$var reg 1 " i0 $end
$var reg 1 # i1 $end
$var reg 1 $ i2 $end
$var reg 1 % i3 $end
$var reg 1 & i4 $end
$var reg 1 ' i5 $end
$var reg 1 ( i6 $end
$var reg 1 ) i7 $end
$var reg 1 * s0 $end
$var reg 1 + s1 $end
$var reg 1 , s2 $end
$scope module uut $end
$var wire 1 " i0 $end
$var wire 1 # i1 $end
$var wire 1 $ i2 $end
$var wire 1 % i3 $end
$var wire 1 & i4 $end
$var wire 1 ' i5 $end
$var wire 1 ( i6 $end
$var wire 1 ) i7 $end
$var wire 1 * s0 $end
$var wire 1 + s1 $end
$var wire 1 , s2 $end
$var wire 1 ! y $end
$upscope $end
$upscope $end
$enddefinitions $end
#0
$dumpvars
0,
0+
0*
0)
0(
0'
0&
0%
0$
0#
1"
1!
$end
#3
0!
0"
#6
1!
1#
1,
#9
0!
0#
#12
1!
1$
0,
1+
#15
0!
0$
#18
1!
1%
1,
#21
0!
0%
#24
1!
1&
0,
0+
1*
#27
0!
0&
#30
1!
1'
1,
#33
0!
0'
#36
1!
1(
0,
1+
#39
0!
0(
#42
1!
1)
1,
#45
0!
0)
