lab-02/orgate/orgate.v
module orgate(a,b,y);
input a,b;
output y;
or(y,a,b);
endmodule

lab-02/orgate/orgate_tb.v
module orgate_tb;
reg a,b;
wire y;
orgate uut(a,b,y);
initial begin
$dumpfile("test_or.vcd");
$dumpvars(0,orgate_tb);
a = 0;
b = 0;
#5
a = 0;
b = 1;
#5
a = 1;
b = 0;
#5
a = 1;
b = 1;
#5
a = 0;
b = 0;
#5
a = 0;
b = 1;
#5
a = 1;
b = 0;
#5
a = 1;
b = 1;
#5
a = 0;
b = 0;
$finish();
end 
endmodule

lab-02/orgate/test_or.vcd
$date
	Sun Nov 12 12:56:28 2023
$end
$version
	Icarus Verilog
$end
$timescale
	1s
$end
$scope module orgate_tb $end
$var wire 1 ! y $end
$var reg 1 " a $end
$var reg 1 # b $end
$scope module uut $end
$var wire 1 " a $end
$var wire 1 # b $end
$var wire 1 ! y $end
$upscope $end
$upscope $end
$enddefinitions $end
#0
$dumpvars
0#
0"
0!
$end
#5
1!
1#
#10
0#
1"
#15
1#
#20
0!
0#
0"
#25
1!
1#
#30
0#
1"
#35
1#
#40
0!
0#
0"
